Metadata-Version: 1.0
Name: simple-fuzzy-equal
Version: 1.0
Summary: Simple compare strings
Home-page: UNKNOWN
Author: UNKNOWN
Author-email: timur20041229@gmail.com
License: UNKNOWN
Platform: UNKNOWN
